README.md
setup.py
src/OCStyleMaster/__init__.py
src/OCStyleMaster/main.py
src/OCStyleMaster/common/__init__.py
src/OCStyleMaster/common/consts.py
src/OCStyleMaster/config/__init__.py
src/OCStyleMaster/config/config.py
src/OCStyleMaster/config/corrector.py
src/OCStyleMaster/config/customerConfig.py
src/OCStyleMaster/fix/__init__.py
src/OCStyleMaster/fix/fix.py
src/OCStyleMaster/globalData/__init__.py
src/OCStyleMaster/globalData/globalData.py
src/OCStyleMaster/managers/__init__.py
src/OCStyleMaster/models/__init__.py
src/OCStyleMaster/models/blocks/__init__.py
src/OCStyleMaster/models/blocks/bigBracket.py
src/OCStyleMaster/models/blocks/bracket.py
src/OCStyleMaster/models/blocks/comment.py
src/OCStyleMaster/models/blocks/fileH.py
src/OCStyleMaster/models/blocks/fileM.py
src/OCStyleMaster/models/blocks/funcBody.py
src/OCStyleMaster/models/blocks/funcH.py
src/OCStyleMaster/models/blocks/funcHead.py
src/OCStyleMaster/models/blocks/funcM.py
src/OCStyleMaster/models/blocks/implement.py
src/OCStyleMaster/models/blocks/interfaceH.py
src/OCStyleMaster/models/blocks/interfaceM.py
src/OCStyleMaster/models/blocks/line.py
src/OCStyleMaster/models/blocks/midBracket.py
src/OCStyleMaster/models/blocks/other.py
src/OCStyleMaster/models/blocks/property.py
src/OCStyleMaster/models/blocks/protocol.py
src/OCStyleMaster/models/blocks/base/__init__.py
src/OCStyleMaster/models/blocks/base/blockBase.py
src/OCStyleMaster/models/blocks/base/file.py
src/OCStyleMaster/models/blocks/test/__init__.py
src/OCStyleMaster/models/blocks/test/funcTest.py
src/OCStyleMaster/models/common/__init__.py
src/OCStyleMaster/models/common/range.py
src/OCStyleMaster/models/error/StyleError.py
src/OCStyleMaster/models/error/__init__.py
src/OCStyleMaster/test/__init__.py
src/OCStyleMaster/test/testMain.py
src/OCStyleMaster/tools/__init__.py
src/OCStyleMaster/tools/blockAnalyzerH.py
src/OCStyleMaster/tools/blockAnalyzerM.py
src/OCStyleMaster/tools/test/__init__.py
src/OCStyleMaster/tools/test/testRegexUtil.py
src/ocstylemaster.egg-info/PKG-INFO
src/ocstylemaster.egg-info/SOURCES.txt
src/ocstylemaster.egg-info/dependency_links.txt
src/ocstylemaster.egg-info/entry_points.txt
src/ocstylemaster.egg-info/top_level.txt