Metadata-Version: 1.0
Name: ocstylemaster
Version: 0.2.3
Summary: Objective-C style checker
Home-page: https://github.com/icefirewang/OCStyleMaster
Author: icefire_wang, Inc.
Author-email: icefire_wang@163.com
License: UNKNOWN
Keywords: pip,Objective-C,OC,style
Platform: UNKNOWN
